llm_mpt30b.py
llm_mpt30b-0.1.dist-info/LICENSE
llm_mpt30b-0.1.dist-info/METADATA
llm_mpt30b-0.1.dist-info/WHEEL
llm_mpt30b-0.1.dist-info/entry_points.txt
llm_mpt30b-0.1.dist-info/top_level.txt
llm_mpt30b-0.1.dist-info/RECORD
