Metadata-Version: 2.1
Name: llm-mpt30b
Version: 0.1
Summary: Plugin for LLM adding support for the MPT-30B language model
Home-page: https://github.com/simonw/llm-mpt30b
Author: Simon Willison
License: Apache License, Version 2.0
Project-URL: Issues, https://github.com/simonw/llm-mpt30b/issues
Project-URL: CI, https://github.com/simonw/llm-mpt30b/actions
Project-URL: Changelog, https://github.com/simonw/llm-mpt30b/releases
Classifier: License :: OSI Approved :: Apache Software License
Requires-Python: >=3.9
License-File: LICENSE
Requires-Dist: llm (>=0.5)
Requires-Dist: ctransformers (>=0.2.10)
Requires-Dist: transformers (>=4.30.2)
Requires-Dist: huggingface-hub
Provides-Extra: test
Requires-Dist: pytest ; extra == 'test'
